CHANGES.rst
CONTRIBUTORS.rst
DEVELOP.rst
LICENSE.GPL
LICENSE.rst
MANIFEST.in
README.rst
setup.cfg
setup.py
docs/index.rst
src/redturtle/__init__.py
src/redturtle.tiles.tileoftiles.egg-info/PKG-INFO
src/redturtle.tiles.tileoftiles.egg-info/SOURCES.txt
src/redturtle.tiles.tileoftiles.egg-info/dependency_links.txt
src/redturtle.tiles.tileoftiles.egg-info/entry_points.txt
src/redturtle.tiles.tileoftiles.egg-info/namespace_packages.txt
src/redturtle.tiles.tileoftiles.egg-info/not-zip-safe
src/redturtle.tiles.tileoftiles.egg-info/requires.txt
src/redturtle.tiles.tileoftiles.egg-info/top_level.txt
src/redturtle/tiles/__init__.py
src/redturtle/tiles/tileoftiles/__init__.py
src/redturtle/tiles/tileoftiles/configure.zcml
src/redturtle/tiles/tileoftiles/eventhandlers.py
src/redturtle/tiles/tileoftiles/interfaces.py
src/redturtle/tiles/tileoftiles/setuphandlers.py
src/redturtle/tiles/tileoftiles/testing.py
src/redturtle/tiles/tileoftiles/tile.pt
src/redturtle/tiles/tileoftiles/tile.py
src/redturtle/tiles/tileoftiles/upgrades.py
src/redturtle/tiles/tileoftiles/upgrades.zcml
src/redturtle/tiles/tileoftiles/browser/__init__.py
src/redturtle/tiles/tileoftiles/browser/configure.zcml
src/redturtle/tiles/tileoftiles/browser/overrides/.gitkeep
src/redturtle/tiles/tileoftiles/browser/static/.gitkeep
src/redturtle/tiles/tileoftiles/locales/redturtle.tiles.tileoftiles.pot
src/redturtle/tiles/tileoftiles/locales/update.sh
src/redturtle/tiles/tileoftiles/locales/it/LC_MESSAGES/redturtle.tiles.tileoftiles.po
src/redturtle/tiles/tileoftiles/profiles/default/browserlayer.xml
src/redturtle/tiles/tileoftiles/profiles/default/metadata.xml
src/redturtle/tiles/tileoftiles/profiles/default/registry.xml
src/redturtle/tiles/tileoftiles/profiles/default/rolemap.xml
src/redturtle/tiles/tileoftiles/profiles/uninstall/browserlayer.xml
src/redturtle/tiles/tileoftiles/tests/__init__.py
src/redturtle/tiles/tileoftiles/tests/test_robot.py
src/redturtle/tiles/tileoftiles/tests/test_setup.py
src/redturtle/tiles/tileoftiles/tests/robot/test_example.robot