Metadata-Version: 1.1
Name: redturtle.tiles.tileoftiles
Version: 1.0a1
Summary: Tile that renders a tile manager
Home-page: https://pypi.org/project/redturtle.tiles.tileoftiles
Author: Luca Bellenghi
Author-email: luca.bellenghi@redturtle.it
License: GPL version 2
Keywords: Python Plone Tile
Platform: UNKNOWN
Classifier: Environment :: Web Environment
Classifier: Framework :: Plone
Classifier: Framework :: Plone :: 5.0
Classifier: Framework :: Plone :: 5.1
Classifier: Programming Language :: Python
Classifier: Programming Language :: Python :: 2.7
Classifier: Operating System :: OS Independent
Classifier: License :: OSI Approved :: GNU General Public License v2 (GPLv2)
